touchv2/__init__.py
touch2-1.0.dist-info/METADATA
touch2-1.0.dist-info/WHEEL
touch2-1.0.dist-info/top_level.txt
touch2-1.0.dist-info/RECORD
